setup.py
csscoco/__init__.py
csscoco/main.py
csscoco.egg-info/PKG-INFO
csscoco.egg-info/SOURCES.txt
csscoco.egg-info/dependency_links.txt
csscoco.egg-info/entry_points.txt
csscoco.egg-info/requires.txt
csscoco.egg-info/top_level.txt
csscoco/css/__init__.py
csscoco/css/__init__.pyc
csscoco/css/gonzales_parser.js
csscoco/css/parse_tree.py
csscoco/css/parser.py
csscoco/css/parser.pyc
csscoco/lang/__init__.py
csscoco/lang/common_.py
csscoco/lang/visitor_decorator.py
csscoco/lang/analysis/__init__.py
csscoco/lang/analysis/expressions.py
csscoco/lang/analysis/pattern_matcher.py
csscoco/lang/analysis/type_checker.py
csscoco/lang/analysis/values.py
csscoco/lang/analysis/violations.py
csscoco/lang/ast/__init__.py
csscoco/lang/ast/ast.py
csscoco/lang/ast/types.py
csscoco/lang/syntax/__init__.py
csscoco/lang/syntax/ast_builder.py
csscoco/lang/syntax/cocoLexer.py
csscoco/lang/syntax/cocoListener.py
csscoco/lang/syntax/cocoParser.py
csscoco/lang/syntax/cocoVisitor.py
csscoco/lang/syntax/error_listener.py
csscoco/node_modules/gonzales/MIT-LICENSE.txt
csscoco/node_modules/gonzales/package.json
csscoco/node_modules/gonzales/lib/cssp.translator.node.js
csscoco/node_modules/gonzales/lib/gonzales.cssp.node.js
csscoco/node_modules/gonzales/lib/gonzales.js
csscoco/node_modules/gonzales/src/cssp.ast.shared.js
csscoco/node_modules/gonzales/src/cssp.translator.node.js
csscoco/node_modules/gonzales/src/cssp.translator.shared.js
csscoco/node_modules/gonzales/src/gonzales.cssp.footer.js
csscoco/node_modules/gonzales/src/gonzales.cssp.header.js
csscoco/node_modules/gonzales/src/gonzales.cssp.node.js
csscoco/node_modules/gonzales/src/tokenizer.shared.js
csscoco/node_modules/gonzales/web/cssp.translator.js
csscoco/node_modules/gonzales/web/gonzales.cssp.web.js