Metadata-Version: 1.1
Name: csscoco
Version: 0.1.18
Summary: A DSL for CSS Code Convetions
Home-page: https://github.com/boryanagoncharenko/CssCoco
Author: Boryana Goncharenko
Author-email: boryana.goncharenko@gmail.com
License: UNKNOWN
Keywords: css code conventions web development
Platform: UNKNOWN
Classifier: Development Status :: 3 - Alpha
Classifier: Intended Audience :: Developers
Classifier: Programming Language :: Python :: 3.4
